_fastrdp.cp312-win32.pyd
fastrdp/RamerDouglasPeucker.h
fastrdp/__init__.py
fastrdp/__init__.pyi
fastrdp/wrapper.cpp
fastrdp-0.3.2.dist-info/licenses/LICENSE
fastrdp-0.3.2.dist-info/METADATA
fastrdp-0.3.2.dist-info/WHEEL
fastrdp-0.3.2.dist-info/top_level.txt
fastrdp-0.3.2.dist-info/RECORD
