Metadata-Version: 2.4
Name: fastrdp
Version: 0.3.2
Summary: Implementation of the Ramer-Douglas-Peucker algorithm
Author: Robert Dahl Jacobsen
License-Expression: MIT
Project-URL: Homepage, https://github.com/robertdj/fastrdp
Classifier: Programming Language :: Python :: 3
Requires-Python: >=3.10
License-File: LICENSE
Requires-Dist: numpy>=2.1.0
Dynamic: license-file
